metalist/__init__.py
metalist/app.py
metalist/config.py
metalist/static/css/app.css
metalist/static/css/dark-theme.css
metalist/static/css/reserved-tags.css
metalist/static/css/unreset.css
metalist/static/css/components/chat-ui.css
metalist/static/css/components/items-list.css
metalist/static/css/components/search-bar.css
metalist/static/css/components/suggestions-list.css
metalist/static/css/components/tags-bar.css
metalist/static/html/index.html
metalist/static/img/caret-down-filled.svg
metalist/static/img/caret-right-filled.svg
metalist/static/img/chat-left-svgrepo-com.svg
metalist/static/img/checkbox-checked.svg
metalist/static/img/checkbox-unchecked.svg
metalist/static/img/favicon.ico
metalist/static/img/search.svg
metalist/static/img/tag.svg
metalist/static/js/app-state.js
metalist/static/js/config.js
metalist/static/js/pub-sub-events.js
metalist/static/js/components/chat-ui.js
metalist/static/js/components/items-list.js
metalist/static/js/components/search-bar.js
metalist/static/js/components/suggestions-list.js
metalist/static/js/components/tags-bar.js
metalist/static/js/misc/item-formatter.js
metalist/static/js/misc/logging.js
metalist/static/js/misc/parsing.js
metalist/static/js/misc/scrolling.js
metalist/static/js/misc/server-proxy.js
metalist/static/js/misc/vdom.js
metalist/static/libs/PubSubJS/LICENSE.md
metalist/static/libs/PubSubJS/pubsub.js
metalist/static/libs/katex/LICENSE
metalist/static/libs/katex/katex.min.css
metalist/static/libs/katex/katex.min.js
metalist/static/libs/katex/contrib/auto-render.min.js
metalist/static/libs/katex/contrib/copy-tex.min.css
metalist/static/libs/katex/contrib/copy-tex.min.js
metalist/static/libs/katex/contrib/mathtex-script-type.min.js
metalist/static/libs/lodash/LICENSE
metalist/static/libs/lodash/lodash.js
metalist/static/libs/markdown-it/LICENSE
metalist/static/libs/markdown-it/markdown-it.min.js
metalist/static/libs/micronitjs/LICENSE
metalist/static/libs/micronitjs/micronit.js
MetaList-0.1.11.dist-info/LICENSE
MetaList-0.1.11.dist-info/METADATA
MetaList-0.1.11.dist-info/WHEEL
MetaList-0.1.11.dist-info/entry_points.txt
MetaList-0.1.11.dist-info/top_level.txt
MetaList-0.1.11.dist-info/RECORD
