Metadata-Version: 2.1
Name: MetaList
Version: 0.1.11
Summary: A PKM web app integrated with LLMs
Home-page: https://github.com/evolvingstuff/MetaList
Author: Thomas Lahore
Author-email: tom.lahore@gmail.com
Classifier: Programming Language :: Python :: 3.8
Classifier: License :: OSI Approved :: MIT License
Classifier: Operating System :: OS Independent
Requires-Python: >=3.8
License-File: LICENSE
Requires-Dist: bottle ==0.12.25
Requires-Dist: bottle-sqlite ==0.2.0
Requires-Dist: beautifulsoup4 ~=4.12.2
Requires-Dist: requests ==2.31.0
Requires-Dist: tqdm ==4.66.1
